poezio/__init__.py
poezio/__main__.py
poezio/args.py
poezio/asyncio.py
poezio/bookmarks.py
poezio/colors.py
poezio/common.py
poezio/config.py
poezio/connection.py
poezio/contact.py
poezio/daemon.py
poezio/decorators.py
poezio/default_config.cfg
poezio/events.py
poezio/fifo.py
poezio/fixes.py
poezio/keyboard.py
poezio/logger.py
poezio/multiuserchat.py
poezio/pep.py
poezio/plugin.py
poezio/plugin_manager.py
poezio/poezio.py
poezio/poezio_shlex.py
poezio/poopt.py
poezio/roster.py
poezio/roster_sorting.py
poezio/size_manager.py
poezio/text_buffer.py
poezio/theming.py
poezio/timed_events.py
poezio/user.py
poezio/xdg.py
poezio/xhtml.py
poezio/core/__init__.py
poezio/core/commands.py
poezio/core/completions.py
poezio/core/core.py
poezio/core/handlers.py
poezio/core/structs.py
poezio/core/tabs.py
poezio/tabs/__init__.py
poezio/tabs/adhoc_commands_list.py
poezio/tabs/basetabs.py
poezio/tabs/bookmarkstab.py
poezio/tabs/confirmtab.py
poezio/tabs/conversationtab.py
poezio/tabs/data_forms.py
poezio/tabs/listtab.py
poezio/tabs/muclisttab.py
poezio/tabs/muctab.py
poezio/tabs/privatetab.py
poezio/tabs/rostertab.py
poezio/tabs/xmltab.py
poezio/windows/__init__.py
poezio/windows/base_wins.py
poezio/windows/bookmark_forms.py
poezio/windows/confirm.py
poezio/windows/data_forms.py
poezio/windows/funcs.py
poezio/windows/image.py
poezio/windows/info_bar.py
poezio/windows/info_wins.py
poezio/windows/input_placeholders.py
poezio/windows/inputs.py
poezio/windows/list.py
poezio/windows/misc.py
poezio/windows/muc.py
poezio/windows/roster_win.py
poezio/windows/text_win.py
poezio-0.12.data/data/share/doc/poezio/source/commands.rst
poezio-0.12.data/data/share/doc/poezio/source/conf.py
poezio-0.12.data/data/share/doc/poezio/source/configuration.rst
poezio-0.12.data/data/share/doc/poezio/source/index.rst
poezio-0.12.data/data/share/doc/poezio/source/install.rst
poezio-0.12.data/data/share/doc/poezio/source/keys.rst
poezio-0.12.dist-info/METADATA
poezio-0.12.dist-info/RECORD
poezio-0.12.dist-info/WHEEL
poezio-0.12.dist-info/entry_points.txt
poezio-0.12.dist-info/top_level.txt
