Metadata-Version: 2.1
Name: poezio
Version: 0.12
Summary: A console XMPP client
Home-page: https://poez.io/
Author: Florent Le Coz
Author-email: louiz@louiz.org
Maintainer: Mathieu Pasquet
Maintainer-email: mathieui@mathieui.net
License: zlib
Download-URL: https://dev.louiz.org/projects/poezio/files
Keywords: jabber,xmpp,client,chat,im,console
Platform: UNKNOWN
Classifier: Development Status :: 5 - Production/Stable
Classifier: Topic :: Communications :: Chat
Classifier: Topic :: Internet :: XMPP
Classifier: Environment :: Console :: Curses
Classifier: Intended Audience :: End Users/Desktop
Classifier: License :: OSI Approved :: zlib/libpng License
Classifier: Natural Language :: English
Classifier: Operating System :: Unix
Classifier: Programming Language :: Python :: 3.7
Classifier: Programming Language :: Python :: 3.6
Classifier: Programming Language :: Python :: 3.5
Classifier: Programming Language :: Python :: 3 :: Only
Provides-Extra: Avoiding cython
Provides-Extra: OTR plugin
Provides-Extra: Screen autoaway plugin
Requires-Dist: slixmpp (>=1.3.0)
Requires-Dist: aiodns
Requires-Dist: pyasn1-modules
Requires-Dist: pyasn1
Provides-Extra: Avoiding cython
Requires-Dist: cffi; extra == 'Avoiding cython'
Provides-Extra: OTR plugin
Requires-Dist: python-potr (>=1.0); extra == 'OTR plugin'
Provides-Extra: Screen autoaway plugin
Requires-Dist: pyinotify (==0.9.4); extra == 'Screen autoaway plugin'
